{"n":"HR: Arena Sport 6 HD","p":[{"s":1784844000,"e":1784898000,"t":"NAJAVA PROGRAMA. Najava","d":""},{"s":1784898000,"e":1784905200,"t":"Nogomet. LENS – MARSEILLE. Francuska Liga","d":""},{"s":1784905200,"e":1784912400,"t":"Nogomet. MILAN – LAZIO. Talijanska Liga","d":""},{"s":1784912400,"e":1784919600,"t":"Nogomet. OSASUNA – BARCELONA. Španjolska Liga","d":""},{"s":1784919600,"e":1784926800,"t":"Nogomet. BAYER LEVERKUSEN – BAYERN. Njemački Kup","d":""},{"s":1784926800,"e":1784930400,"t":"Nogomet. AKHMAT – PARI NN. Ruska Liga","d":""},{"s":1784930400,"e":1784984400,"t":"NAJAVA PROGRAMA. Najava","d":""},{"s":1784984400,"e":1784991600,"t":"Nogomet. RENNES – LILLE. Francuska Liga","d":""},{"s":1784991600,"e":1784998800,"t":"Nogomet. LAZIO – ROMA. Talijanska Liga","d":""},{"s":1784998800,"e":1785006000,"t":"Nogomet. REAL MADRID – BARCELONA. Španjolska Liga","d":""},{"s":1785006000,"e":1785013200,"t":"Nogomet. STUTTGART – FREIBURG. Njemački Kup","d":""},{"s":1785013200,"e":1785016800,"t":"Nogomet. CSKA – ZENIT. Ruska Liga","d":""},{"s":1785016800,"e":1785070800,"t":"NAJAVA PROGRAMA. Najava","d":""}]}