{"n":"TR: Bein Sports 4 HD","p":[{"s":1784839500,"e":1784861100,"t":"Ligue 1 Haftanın Golleri","d":""},{"s":1784861100,"e":1784862000,"t":"Ligue 1 Haftanın Golleri","d":""},{"s":1784862000,"e":1784868300,"t":"Marseille - Metz","d":""},{"s":1784868300,"e":1784869200,"t":"Ligue 1 Haftanın Golleri","d":""},{"s":1784869200,"e":1784875500,"t":"O.Lyon - Lorient","d":""},{"s":1784875500,"e":1784876400,"t":"Ligue 1 Haftanın Golleri","d":""},{"s":1784876400,"e":1784882700,"t":"Lens - Paris Saint Germain","d":""},{"s":1784882700,"e":1784883600,"t":"Ligue 1 Haftanın Golleri","d":""},{"s":1784883600,"e":1784889900,"t":"Toulouse - Lille","d":""},{"s":1784889900,"e":1784890800,"t":"Ligue 1 Haftanın Golleri","d":""},{"s":1784890800,"e":1784897100,"t":"Paris FC - Monaco","d":""},{"s":1784897100,"e":1784898000,"t":"Ligue 1 Haftanın Golleri","d":""},{"s":1784898000,"e":1784904300,"t":"Rennes - Angers","d":""},{"s":1784904300,"e":1784905200,"t":"Ligue 1 Haftanın Golleri","d":""},{"s":1784905200,"e":1784911500,"t":"Marseille - Metz","d":""},{"s":1784911500,"e":1784912400,"t":"Ligue 1 Haftanın Golleri","d":""},{"s":1784912400,"e":1784918700,"t":"O.Lyon - Lorient","d":""},{"s":1784918700,"e":1784919600,"t":"Ligue 1 Haftanın Golleri","d":""},{"s":1784919600,"e":1784925900,"t":"Lens - Paris Saint Germain","d":""},{"s":1784925900,"e":1784947500,"t":"Ligue 1 Haftanın Golleri","d":""},{"s":1784947500,"e":1784948400,"t":"Ligue 1 Haftanın Golleri","d":""},{"s":1784948400,"e":1784954700,"t":"Strasbourg - Rennes","d":""},{"s":1784954700,"e":1784955600,"t":"Ligue 1 Haftanın Golleri","d":""},{"s":1784955600,"e":1784961900,"t":"Metz - Paris FC","d":""},{"s":1784961900,"e":1784962800,"t":"Ligue 1 Haftanın Golleri","d":""},{"s":1784962800,"e":1784969100,"t":"Paris Saint Germain - Lyon","d":""},{"s":1784969100,"e":1784970000,"t":"Ligue 1 Haftanın Golleri","d":""},{"s":1784970000,"e":1784976300,"t":"Lens - Toulouse","d":""},{"s":1784976300,"e":1784977200,"t":"Ligue 1 Haftanın Golleri","d":""},{"s":1784977200,"e":1784983500,"t":"Lorient - Marseille","d":""},{"s":1784983500,"e":1784984400,"t":"Ligue 1 Haftanın Golleri","d":""},{"s":1784984400,"e":1784990700,"t":"Monaco - Auxerre","d":""},{"s":1784990700,"e":1784991600,"t":"Ligue 1 Haftanın Golleri","d":""},{"s":1784991600,"e":1784997900,"t":"Strasbourg - Rennes","d":""},{"s":1784997900,"e":1784998800,"t":"Ligue 1 Haftanın Golleri","d":""},{"s":1784998800,"e":1785005100,"t":"Metz - Paris FC","d":""},{"s":1785005100,"e":1785006000,"t":"Ligue 1 Haftanın Golleri","d":""},{"s":1785006000,"e":1785012300,"t":"Paris Saint Germain - Lyon","d":""},{"s":1785012300,"e":1785033900,"t":"Ligue 1 Haftanın Golleri","d":""}]}