{"n":"IL: Eurosport 1 HD","p":[{"s":1784849400,"e":1784854800,"t":"טור דה פראנס 2026","d":"שידור חוזר: טור דה פראנס 2026, קטע 18: 185.2 ק''מ. מירוץ האופניים המפורסם בעולם נערך זו הפעם ה-113, בתאריכים 04-26/07. אשתקד ניצח טאדיי פוגאצ'אר (סלובניה)."},{"s":1784854800,"e":1784862000,"t":"סנוקר","d":"שידור חוזר: גמר אליפות העולם בסנוקר לשנת 2026 משפילד, אנגליה: שון מרפי (אנגליה) נגד וו ייזה (סין)."},{"s":1784862000,"e":1784869200,"t":"טור דה פראנס 2026","d":"שידור חוזר: טור דה פראנס 2026, קטע 18: 185.2 ק''מ. מירוץ האופניים המפורסם בעולם נערך זו הפעם ה-113, בתאריכים 04-26/07. אשתקד ניצח טאדיי פוגאצ'אר (סלובניה)."},{"s":1784869200,"e":1784874600,"t":"הסבב העולמי","d":"שידור חוזר: תחרות במסגרת הסבב העולמי בטריאתלון."},{"s":1784874600,"e":1784880000,"t":"טור דה פראנס 2026","d":"שידור חוזר: טור דה פראנס 2026, קטע 18: 185.2 ק''מ. מירוץ האופניים המפורסם בעולם נערך זו הפעם ה-113, בתאריכים 04-26/07. אשתקד ניצח טאדיי פוגאצ'אר (סלובניה)."},{"s":1784880000,"e":1784887200,"t":"הסבב העולמי","d":"שידור חוזר: תחרות במסגרת הסבב העולמי בטריאתלון."},{"s":1784887200,"e":1784889000,"t":"אופני הרים","d":"שידור חוזר: אופני הרים: סבב גביע העולם."},{"s":1784889000,"e":1784893500,"t":"טור דה פראנס 2026","d":"שידור חוזר: טור דה פראנס 2026, קטע 18: 185.2 ק''מ. מירוץ האופניים המפורסם בעולם נערך זו הפעם ה-113, בתאריכים 04-26/07. אשתקד ניצח טאדיי פוגאצ'אר (סלובניה)."},{"s":1784893500,"e":1784907900,"t":"ישיר! טור דה פראנס 2026","d":"שידור ישיר: טור דה פראנס 2026, קטע 19: 127.9 ק''מ. מירוץ האופניים המפורסם בעולם נערך זו הפעם ה-113, בתאריכים 04-26/07. אשתקד ניצח טאדיי פוגאצ'אר (סלובניה)."},{"s":1784907900,"e":1784908800,"t":"ישיר! טור דה פראנס 2026","d":"שידור ישיר: טור דה פראנס 2026, קטע 19: 127.9 ק''מ. מירוץ האופניים המפורסם בעולם נערך זו הפעם ה-113, בתאריכים 04-26/07. אשתקד ניצח טאדיי פוגאצ'אר (סלובניה)."},{"s":1784908800,"e":1784912400,"t":"הטור של פולין: מירוץ הנשים","d":"מירוץ אופניים. הטור של פולין: מירוץ הנשים."},{"s":1784912400,"e":1784914200,"t":"אופני הרים","d":"שידור חוזר: אופני הרים: סבב גביע העולם."},{"s":1784914200,"e":1784916000,"t":"הסבב העולמי","d":"שידור חוזר: תחרות במסגרת הסבב העולמי בטריאתלון."},{"s":1784916000,"e":1784925000,"t":"ישיר! משחקי חבר העמים הבריטי 2026","d":"שידור ישיר: משחקי חבר העמים הבריטי 2026 אשר נערכים בגלאזגו, סקוטלנד: שחייה."},{"s":1784925000,"e":1784930400,"t":"טור דה פראנס 2026","d":"שידור חוזר: טור דה פראנס 2026, קטע 19: 127.9 ק''מ. מירוץ האופניים המפורסם בעולם נערך זו הפעם ה-113, בתאריכים 04-26/07. אשתקד ניצח טאדיי פוגאצ'אר (סלובניה)."},{"s":1784930400,"e":1784934000,"t":"הטור של פולין: מירוץ הנשים","d":"שידור חוזר: מירוץ אופניים. הטור של פולין: מירוץ הנשים."},{"s":1784934000,"e":1784935800,"t":"אופני הרים","d":"שידור חוזר: אופני הרים: סבב גביע העולם."},{"s":1784935800,"e":1784941200,"t":"טור דה פראנס 2026","d":"שידור חוזר: טור דה פראנס 2026, קטע 19: 127.9 ק''מ. מירוץ האופניים המפורסם בעולם נערך זו הפעם ה-113, בתאריכים 04-26/07. אשתקד ניצח טאדיי פוגאצ'אר (סלובניה)."},{"s":1784941200,"e":1784948400,"t":"משחקי חבר העמים הבריטי 2026","d":"שידור חוזר: משחקי חבר העמים הבריטי 2026 אשר נערכים בגלאזגו, סקוטלנד: שחייה."},{"s":1784948400,"e":1784955600,"t":"טור דה פראנס 2026","d":"שידור חוזר: טור דה פראנס 2026, קטע 19: 127.9 ק''מ. מירוץ האופניים המפורסם בעולם נערך זו הפעם ה-113, בתאריכים 04-26/07. אשתקד ניצח טאדיי פוגאצ'אר (סלובניה)."},{"s":1784955600,"e":1784959200,"t":"משחקי חבר העמים הבריטי 2026","d":"משחקי חבר העמים הבריטי 2026 אשר נערכים בגלאזגו, סקוטלנד: סיכום אירועי היום."},{"s":1784959200,"e":1784961000,"t":"אופני הרים","d":"שידור חוזר: אופני הרים: סבב גביע העולם."},{"s":1784961000,"e":1784968200,"t":"משחקי חבר העמים הבריטי 2026","d":"שידור חוזר: משחקי חבר העמים הבריטי 2026 אשר נערכים בגלאזגו, סקוטלנד: שחייה."},{"s":1784968200,"e":1784970000,"t":"טור דה פראנס 2026","d":"שידור חוזר: טור דה פראנס 2026, קטע 19: 127.9 ק''מ. מירוץ האופניים המפורסם בעולם נערך זו הפעם ה-113, בתאריכים 04-26/07. אשתקד ניצח טאדיי פוגאצ'אר (סלובניה)."},{"s":1784970000,"e":1784984400,"t":"ישיר! טור דה פראנס 2026","d":"שידור ישיר: טור דה פראנס 2026, קטע 20: 170.9 ק''מ. מירוץ האופניים המפורסם בעולם נערך זו הפעם ה-113, בתאריכים 04-26/07. אשתקד ניצח טאדיי פוגאצ'אר (סלובניה)."},{"s":1784984400,"e":1784991600,"t":"ישיר! טור דה פראנס 2026","d":"שידור ישיר: טור דה פראנס 2026, קטע 20: 170.9 ק''מ. מירוץ האופניים המפורסם בעולם נערך זו הפעם ה-113, בתאריכים 04-26/07. אשתקד ניצח טאדיי פוגאצ'אר (סלובניה)."},{"s":1784991600,"e":1784995200,"t":"הטור של פולין: מירוץ הנשים","d":"מירוץ אופניים. הטור של פולין: מירוץ הנשים."},{"s":1784995200,"e":1784998800,"t":"פורמולה E","d":"מירוצים. פורמולה E מטוקיו, יפן."},{"s":1784998800,"e":1785002400,"t":"סיף","d":"שידור חוזר: סיף. אליפות העולם אשר נערכת בהונג קונג."},{"s":1785002400,"e":1785011400,"t":"ישיר! משחקי חבר העמים הבריטי 2026","d":"שידור ישיר: משחקי חבר העמים הבריטי 2026 אשר נערכים בגלאזגו, סקוטלנד: שחייה."},{"s":1785011400,"e":1785016800,"t":"סיף","d":"שידור חוזר: סיף. אליפות העולם אשר נערכת בהונג קונג."},{"s":1785016800,"e":1785022200,"t":"מירוצי שטח","d":"שידור חוזר: מירוצי שטח: הסבב העולמי."},{"s":1785022200,"e":1785027600,"t":"טור דה פראנס 2026","d":"שידור חוזר: טור דה פראנס 2026, קטע 20: 170.9 ק''מ. מירוץ האופניים המפורסם בעולם נערך זו הפעם ה-113, בתאריכים 04-26/07. אשתקד ניצח טאדיי פוגאצ'אר (סלובניה)."}]}