{"n":"Oasis Comedy","p":[{"s":1784850975,"e":1784857275,"t":"Дурные деньги (2023)","d":"Дурные деньги (2023)"},{"s":1784857275,"e":1784862624,"t":"Дюплекс (2003)","d":"Дюплекс (2003)"},{"s":1784862624,"e":1784868134,"t":"Евротур (2004)","d":"Евротур (2004)"},{"s":1784868134,"e":1784874872,"t":"За бортом (2018)","d":"За бортом (2018)"},{"s":1784874872,"e":1784880738,"t":"Загадочное убийство (2019)","d":"Загадочное убийство (2019)"},{"s":1784880738,"e":1784887155,"t":"Залечь на дно в Брюгге (2008)","d":"Залечь на дно в Брюгге (2008)"},{"s":1784887155,"e":1784894288,"t":"Зелёный Шершень (2011)","d":"Зелёный Шершень (2011)"},{"s":1784894288,"e":1784901204,"t":"Знакомство с Факерами (2004)","d":"Знакомство с Факерами (2004)"},{"s":1784901204,"e":1784907070,"t":"Знакомство с Факерами 2 (2010)","d":"Знакомство с Факерами 2 (2010)"},{"s":1784907070,"e":1784914171,"t":"Кейт и Лео (2001)","d":"Кейт и Лео (2001)"},{"s":1784914171,"e":1784920142,"t":"Клерки (1994)","d":"Клерки (1994)"},{"s":1784920142,"e":1784926593,"t":"Клик С пультом по жизни (2006)","d":"Клик С пультом по жизни (2006)"},{"s":1784926593,"e":1784932226,"t":"Король вечеринок (2002)","d":"Король вечеринок (2002)"},{"s":1784932226,"e":1784938872,"t":"Космический кадет (2024)","d":"Космический кадет (2024)"},{"s":1784938872,"e":1784946648,"t":"Кровью и потом Анаболики (2013)","d":"Кровью и потом Анаболики (2013)"},{"s":1784946648,"e":1784953151,"t":"Кролик Джоджо (2019)","d":"Кролик Джоджо (2019)"},{"s":1784953151,"e":1784961201,"t":"Круэлла (2021)","d":"Круэлла (2021)"},{"s":1784961201,"e":1784967510,"t":"Крылышко или ножка (1976)","d":"Крылышко или ножка (1976)"},{"s":1784967510,"e":1784975047,"t":"Кунг-фу жеребец (2023)","d":"Кунг-фу жеребец (2023)"},{"s":1784975047,"e":1784982191,"t":"Любовь без памяти (2023)","d":"Любовь без памяти (2023)"},{"s":1784982191,"e":1784988009,"t":"Майор Пэйн (1995)","d":"Майор Пэйн (1995)"},{"s":1784988009,"e":1784993866,"t":"Мальчишник 2 Из Вегаса в Бангкок (2011)","d":"Мальчишник 2 Из Вегаса в Бангкок (2011)"},{"s":1784993866,"e":1785000340,"t":"Мальчишник в Вегасе (2009)","d":"Мальчишник в Вегасе (2009)"},{"s":1785000340,"e":1785006349,"t":"Мальчишник Часть III (2013)","d":"Мальчишник Часть III (2013)"},{"s":1785006349,"e":1785013282,"t":"Марли и я (2008)","d":"Марли и я (2008)"},{"s":1785013282,"e":1785019875,"t":"Мы - Миллеры (2013)","d":"Мы - Миллеры (2013)"},{"s":1785019875,"e":1785026473,"t":"Напряги извилины (2008)","d":"Напряги извилины (2008)"}]}