{"n":"TVPlay Великая Отечественная HD","p":[{"s":1784848506,"e":1784852154,"t":"Освобождение фильм 3 часть 1","d":"Освобождение фильм 3 часть 1"},{"s":1784852154,"e":1784856123,"t":"Освобождение фильм 3 часть 2","d":"Освобождение фильм 3 часть 2"},{"s":1784856123,"e":1784861041,"t":"Освобождение фильм 5","d":"Освобождение фильм 5"},{"s":1784861041,"e":1784865489,"t":"Освобождение фильм 6","d":"Освобождение фильм 6"},{"s":1784865489,"e":1784872523,"t":"Ржев 2019","d":"Ржев 2019"},{"s":1784872523,"e":1784878583,"t":"Судьба человека 1959","d":"Судьба человека 1959"},{"s":1784878583,"e":1784885955,"t":"Битва за Севастополь 2015","d":"Битва за Севастополь 2015"},{"s":1784885955,"e":1784893193,"t":"28 Панфиловцев 2016","d":"28 Панфиловцев 2016"},{"s":1784893193,"e":1784899448,"t":"Белый Тигр 2012","d":"Белый Тигр 2012"},{"s":1784899448,"e":1784904322,"t":"Битва за Москву 1 серия 1985","d":"Битва за Москву 1 серия 1985"},{"s":1784904322,"e":1784909844,"t":"Битва за Москву 2 серия 1985","d":"Битва за Москву 2 серия 1985"},{"s":1784909844,"e":1784915042,"t":"Битва за Москву 3 серия 1985","d":"Битва за Москву 3 серия 1985"},{"s":1784915042,"e":1784920601,"t":"Битва за Москву 4 серия 1985","d":"Битва за Москву 4 серия 1985"},{"s":1784920601,"e":1784926047,"t":"Сталинград 1989 1 серия","d":"Сталинград 1989 1 серия"},{"s":1784926047,"e":1784932178,"t":"Сталинград 1989 2 серия","d":"Сталинград 1989 2 серия"},{"s":1784932178,"e":1784940526,"t":"Т-34 2018","d":"Т-34 2018"},{"s":1784940526,"e":1784947303,"t":"Собибор 2018","d":"Собибор 2018"},{"s":1784947303,"e":1784955108,"t":"Нюрнберг 2023","d":"Нюрнберг 2023"}]}